giodemo/__init__.py
giodemo/giodemo.py
giodemo-0.0.2.dist-info/LICENSE
giodemo-0.0.2.dist-info/METADATA
giodemo-0.0.2.dist-info/WHEEL
giodemo-0.0.2.dist-info/top_level.txt
giodemo-0.0.2.dist-info/RECORD
