Metadata-Version: 2.1
Name: giodemo
Version: 0.0.2
Summary: A Python package for interactive mapping
Home-page: https://github.com/S-VAZQ/giodemo
Author: Sergio Vazquez
Author-email: sergiov12@live.com
License: MIT license
Keywords: giodemo
Platform: UNKNOWN
Classifier: Development Status :: 2 - Pre-Alpha
Classifier: Intended Audience :: Developers
Classifier: License :: OSI Approved :: MIT License
Classifier: Natural Language :: English
Classifier: Programming Language :: Python :: 3
Classifier: Programming Language :: Python :: 3.5
Classifier: Programming Language :: Python :: 3.6
Classifier: Programming Language :: Python :: 3.7
Classifier: Programming Language :: Python :: 3.8
Requires-Python: >=3.5
